{
  "experiment": "fashion_mnist_l4000_p0.3_init_LG_LC",
  "config": {
    "epochs": 500,
    "warmup": 10,
    "batch_size": 256,
    "lr": 0.03,
    "momentum": 0.9,
    "weight_decay": 0.0005,
    "tau": 3.0,
    "unlabeled_tau": 2.0,
    "use_ema": false,
    "ema_decay": 0.999,
    "device": "cuda",
    "num_workers": 4,
    "seed": 42,
    "print_interval": 10,
    "dataset": "fashion_mnist",
    "model_name": "lenet",
    "in_ch": 1,
    "num_labeled": 4000,
    "partial_rate": 0.3
  },
  "ablation_flags": {
    "use_init": true,
    "use_LG": true,
    "use_LC": true
  },
  "final_accuracy": 17.87,
  "results": [
    {
      "epoch": 0,
      "loss": 2.26042809182025,
      "accuracy": 10.0
    },
    {
      "epoch": 1,
      "loss": 1.978800186705082,
      "accuracy": 10.0
    },
    {
      "epoch": 2,
      "loss": 1.944908055346063,
      "accuracy": 11.63
    },
    {
      "epoch": 3,
      "loss": 1.922646136486784,
      "accuracy": 19.87
    },
    {
      "epoch": 4,
      "loss": 1.9189302672731114,
      "accuracy": 22.68
    },
    {
      "epoch": 5,
      "loss": 1.8749742391261648,
      "accuracy": 20.14
    },
    {
      "epoch": 6,
      "loss": 1.879983872555672,
      "accuracy": 18.05
    },
    {
      "epoch": 7,
      "loss": 1.8739405068945378,
      "accuracy": 19.09
    },
    {
      "epoch": 8,
      "loss": 1.8526386763187166,
      "accuracy": 24.01
    },
    {
      "epoch": 9,
      "loss": 1.8406935808506417,
      "accuracy": 21.81
    },
    {
      "epoch": 10,
      "loss": 0.6409435552485445,
      "accuracy": 22.23
    },
    {
      "epoch": 11,
      "loss": 0.4331189605783909,
      "accuracy": 15.08
    },
    {
      "epoch": 12,
      "loss": 0.41800340528183794,
      "accuracy": 16.72
    },
    {
      "epoch": 13,
      "loss": 0.3751143701533054,
      "accuracy": 15.99
    },
    {
      "epoch": 14,
      "loss": 0.36360478889434894,
      "accuracy": 17.11
    },
    {
      "epoch": 15,
      "loss": 0.3442852098256984,
      "accuracy": 16.74
    },
    {
      "epoch": 16,
      "loss": 0.33558165608568397,
      "accuracy": 17.72
    },
    {
      "epoch": 17,
      "loss": 0.33229901061413136,
      "accuracy": 18.0
    },
    {
      "epoch": 18,
      "loss": 0.32523159968092086,
      "accuracy": 16.57
    },
    {
      "epoch": 19,
      "loss": 0.3210696653482762,
      "accuracy": 17.47
    },
    {
      "epoch": 20,
      "loss": 0.3185468398510142,
      "accuracy": 16.97
    },
    {
      "epoch": 21,
      "loss": 0.31665133592930245,
      "accuracy": 16.97
    },
    {
      "epoch": 22,
      "loss": 0.3123902012693121,
      "accuracy": 16.99
    },
    {
      "epoch": 23,
      "loss": 0.30970450975793473,
      "accuracy": 16.53
    },
    {
      "epoch": 24,
      "loss": 0.31007339542216444,
      "accuracy": 17.59
    },
    {
      "epoch": 25,
      "loss": 0.30806063413619994,
      "accuracy": 16.65
    },
    {
      "epoch": 26,
      "loss": 0.3050295276844755,
      "accuracy": 16.74
    },
    {
      "epoch": 27,
      "loss": 0.3046769636742612,
      "accuracy": 17.96
    },
    {
      "epoch": 28,
      "loss": 0.3013770617703174,
      "accuracy": 16.57
    },
    {
      "epoch": 29,
      "loss": 0.29953362174490666,
      "accuracy": 16.0
    },
    {
      "epoch": 30,
      "loss": 0.29825414476242473,
      "accuracy": 16.23
    },
    {
      "epoch": 31,
      "loss": 0.30141478047726,
      "accuracy": 16.44
    },
    {
      "epoch": 32,
      "loss": 0.29959376092920914,
      "accuracy": 16.49
    },
    {
      "epoch": 33,
      "loss": 0.29825582561340735,
      "accuracy": 16.21
    },
    {
      "epoch": 34,
      "loss": 0.2938156578769075,
      "accuracy": 16.24
    },
    {
      "epoch": 35,
      "loss": 0.2935799833941967,
      "accuracy": 16.32
    },
    {
      "epoch": 36,
      "loss": 0.29337918599869345,
      "accuracy": 15.67
    },
    {
      "epoch": 37,
      "loss": 0.29366554205721995,
      "accuracy": 15.38
    },
    {
      "epoch": 38,
      "loss": 0.2924474226033434,
      "accuracy": 15.56
    },
    {
      "epoch": 39,
      "loss": 0.29211293528688714,
      "accuracy": 15.88
    },
    {
      "epoch": 40,
      "loss": 0.29363175674955894,
      "accuracy": 14.5
    },
    {
      "epoch": 41,
      "loss": 0.2945981466389717,
      "accuracy": 15.38
    },
    {
      "epoch": 42,
      "loss": 0.2928693548478979,
      "accuracy": 15.64
    },
    {
      "epoch": 43,
      "loss": 0.29153411610329405,
      "accuracy": 16.07
    },
    {
      "epoch": 44,
      "loss": 0.29277104101282486,
      "accuracy": 15.06
    },
    {
      "epoch": 45,
      "loss": 0.2940561645842613,
      "accuracy": 15.38
    },
    {
      "epoch": 46,
      "loss": 0.2901995042537121,
      "accuracy": 15.97
    },
    {
      "epoch": 47,
      "loss": 0.2975850463547605,
      "accuracy": 16.27
    },
    {
      "epoch": 48,
      "loss": 0.29455201835074324,
      "accuracy": 16.4
    },
    {
      "epoch": 49,
      "loss": 0.30000309772948003,
      "accuracy": 16.62
    },
    {
      "epoch": 50,
      "loss": 0.2966771937431173,
      "accuracy": 16.11
    },
    {
      "epoch": 51,
      "loss": 0.2970148248241303,
      "accuracy": 16.23
    },
    {
      "epoch": 52,
      "loss": 0.30050073836712127,
      "accuracy": 14.92
    },
    {
      "epoch": 53,
      "loss": 0.30035407486114096,
      "accuracy": 15.99
    },
    {
      "epoch": 54,
      "loss": 0.3013483026560317,
      "accuracy": 16.52
    },
    {
      "epoch": 55,
      "loss": 0.3000681903768093,
      "accuracy": 15.91
    },
    {
      "epoch": 56,
      "loss": 0.3011974135928966,
      "accuracy": 16.37
    },
    {
      "epoch": 57,
      "loss": 0.2987298918531296,
      "accuracy": 15.88
    },
    {
      "epoch": 58,
      "loss": 0.30393555728679006,
      "accuracy": 16.47
    },
    {
      "epoch": 59,
      "loss": 0.30340023218317236,
      "accuracy": 14.99
    },
    {
      "epoch": 60,
      "loss": 0.3029143013218616,
      "accuracy": 15.52
    },
    {
      "epoch": 61,
      "loss": 0.2973587358885623,
      "accuracy": 16.43
    },
    {
      "epoch": 62,
      "loss": 0.30629887105302606,
      "accuracy": 14.24
    },
    {
      "epoch": 63,
      "loss": 0.3047574116194502,
      "accuracy": 16.43
    },
    {
      "epoch": 64,
      "loss": 0.30568353299130785,
      "accuracy": 15.51
    },
    {
      "epoch": 65,
      "loss": 0.3021829314688419,
      "accuracy": 15.21
    },
    {
      "epoch": 66,
      "loss": 0.3060650147022085,
      "accuracy": 14.77
    },
    {
      "epoch": 67,
      "loss": 0.30643652962877393,
      "accuracy": 15.79
    },
    {
      "epoch": 68,
      "loss": 0.303759059183141,
      "accuracy": 15.57
    },
    {
      "epoch": 69,
      "loss": 0.30473007591480905,
      "accuracy": 15.52
    },
    {
      "epoch": 70,
      "loss": 0.3056542893673511,
      "accuracy": 16.07
    },
    {
      "epoch": 71,
      "loss": 0.30459485751517273,
      "accuracy": 15.48
    },
    {
      "epoch": 72,
      "loss": 0.3088589683492133,
      "accuracy": 14.23
    },
    {
      "epoch": 73,
      "loss": 0.30827237906608174,
      "accuracy": 16.63
    },
    {
      "epoch": 74,
      "loss": 0.30455094471256783,
      "accuracy": 15.95
    },
    {
      "epoch": 75,
      "loss": 0.3056843556622241,
      "accuracy": 16.04
    },
    {
      "epoch": 76,
      "loss": 0.3053895560350824,
      "accuracy": 17.16
    },
    {
      "epoch": 77,
      "loss": 0.30652777698445827,
      "accuracy": 16.64
    },
    {
      "epoch": 78,
      "loss": 0.3074532241263288,
      "accuracy": 14.92
    },
    {
      "epoch": 79,
      "loss": 0.3093926618707941,
      "accuracy": 15.49
    },
    {
      "epoch": 80,
      "loss": 0.30356638946748793,
      "accuracy": 16.53
    },
    {
      "epoch": 81,
      "loss": 0.30539156547252166,
      "accuracy": 16.66
    },
    {
      "epoch": 82,
      "loss": 0.30625027418136597,
      "accuracy": 16.2
    },
    {
      "epoch": 83,
      "loss": 0.30876662747022954,
      "accuracy": 16.6
    },
    {
      "epoch": 84,
      "loss": 0.3085006442475826,
      "accuracy": 17.34
    },
    {
      "epoch": 85,
      "loss": 0.30658162572282427,
      "accuracy": 17.0
    },
    {
      "epoch": 86,
      "loss": 0.30429508812884065,
      "accuracy": 16.75
    },
    {
      "epoch": 87,
      "loss": 0.3037381953381478,
      "accuracy": 16.27
    },
    {
      "epoch": 88,
      "loss": 0.30604900809678626,
      "accuracy": 15.45
    },
    {
      "epoch": 89,
      "loss": 0.30699069075127866,
      "accuracy": 16.46
    },
    {
      "epoch": 90,
      "loss": 0.3098740983516612,
      "accuracy": 16.26
    },
    {
      "epoch": 91,
      "loss": 0.3100874648449269,
      "accuracy": 17.42
    },
    {
      "epoch": 92,
      "loss": 0.30925446666301565,
      "accuracy": 17.0
    },
    {
      "epoch": 93,
      "loss": 0.31161143652936246,
      "accuracy": 16.66
    },
    {
      "epoch": 94,
      "loss": 0.3094005825671744,
      "accuracy": 16.41
    },
    {
      "epoch": 95,
      "loss": 0.3085623208512651,
      "accuracy": 16.21
    },
    {
      "epoch": 96,
      "loss": 0.3113751289058239,
      "accuracy": 14.36
    },
    {
      "epoch": 97,
      "loss": 0.3086500070196517,
      "accuracy": 16.32
    },
    {
      "epoch": 98,
      "loss": 0.30753414079229885,
      "accuracy": 15.22
    },
    {
      "epoch": 99,
      "loss": 0.31078224556243167,
      "accuracy": 16.03
    },
    {
      "epoch": 100,
      "loss": 0.3113931265283138,
      "accuracy": 17.04
    },
    {
      "epoch": 101,
      "loss": 0.3097870539477531,
      "accuracy": 16.58
    },
    {
      "epoch": 102,
      "loss": 0.31109469957808233,
      "accuracy": 18.17
    },
    {
      "epoch": 103,
      "loss": 0.31097960224811066,
      "accuracy": 15.45
    },
    {
      "epoch": 104,
      "loss": 0.3107241489785783,
      "accuracy": 17.41
    },
    {
      "epoch": 105,
      "loss": 0.3110783931739787,
      "accuracy": 16.26
    },
    {
      "epoch": 106,
      "loss": 0.31150167616123847,
      "accuracy": 16.68
    },
    {
      "epoch": 107,
      "loss": 0.3108575425883557,
      "accuracy": 15.95
    },
    {
      "epoch": 108,
      "loss": 0.31140995184157755,
      "accuracy": 16.93
    },
    {
      "epoch": 109,
      "loss": 0.3107334341774596,
      "accuracy": 17.06
    },
    {
      "epoch": 110,
      "loss": 0.31001102778505774,
      "accuracy": 16.65
    },
    {
      "epoch": 111,
      "loss": 0.3145516233875396,
      "accuracy": 16.81
    },
    {
      "epoch": 112,
      "loss": 0.31326407213160334,
      "accuracy": 16.9
    },
    {
      "epoch": 113,
      "loss": 0.3102612050923895,
      "accuracy": 16.38
    },
    {
      "epoch": 114,
      "loss": 0.30829459435128154,
      "accuracy": 16.93
    },
    {
      "epoch": 115,
      "loss": 0.31187975634919834,
      "accuracy": 17.71
    },
    {
      "epoch": 116,
      "loss": 0.3111246190172561,
      "accuracy": 17.38
    },
    {
      "epoch": 117,
      "loss": 0.3086713243038096,
      "accuracy": 17.22
    },
    {
      "epoch": 118,
      "loss": 0.30851271336383007,
      "accuracy": 16.61
    },
    {
      "epoch": 119,
      "loss": 0.3125741753806459,
      "accuracy": 17.0
    },
    {
      "epoch": 120,
      "loss": 0.30918538164585196,
      "accuracy": 16.83
    },
    {
      "epoch": 121,
      "loss": 0.31324184403774585,
      "accuracy": 15.21
    },
    {
      "epoch": 122,
      "loss": 0.3099248321449503,
      "accuracy": 16.87
    },
    {
      "epoch": 123,
      "loss": 0.309463125974574,
      "accuracy": 16.76
    },
    {
      "epoch": 124,
      "loss": 0.3067393263603779,
      "accuracy": 17.02
    },
    {
      "epoch": 125,
      "loss": 0.31017478850293667,
      "accuracy": 16.8
    },
    {
      "epoch": 126,
      "loss": 0.3048414017291779,
      "accuracy": 17.4
    },
    {
      "epoch": 127,
      "loss": 0.3101478647678456,
      "accuracy": 16.34
    },
    {
      "epoch": 128,
      "loss": 0.3105444647530292,
      "accuracy": 17.83
    },
    {
      "epoch": 129,
      "loss": 0.31080004395322597,
      "accuracy": 16.11
    },
    {
      "epoch": 130,
      "loss": 0.3083141435334023,
      "accuracy": 17.98
    },
    {
      "epoch": 131,
      "loss": 0.30909487522662954,
      "accuracy": 16.76
    },
    {
      "epoch": 132,
      "loss": 0.3079995555446503,
      "accuracy": 17.07
    },
    {
      "epoch": 133,
      "loss": 0.3071775018851808,
      "accuracy": 17.29
    },
    {
      "epoch": 134,
      "loss": 0.31016001289195205,
      "accuracy": 18.25
    },
    {
      "epoch": 135,
      "loss": 0.3116020952767514,
      "accuracy": 17.21
    },
    {
      "epoch": 136,
      "loss": 0.30933469559283966,
      "accuracy": 17.45
    },
    {
      "epoch": 137,
      "loss": 0.30772829220650044,
      "accuracy": 17.44
    },
    {
      "epoch": 138,
      "loss": 0.3083294622441556,
      "accuracy": 17.19
    },
    {
      "epoch": 139,
      "loss": 0.30584459983287976,
      "accuracy": 16.67
    },
    {
      "epoch": 140,
      "loss": 0.30738185070296553,
      "accuracy": 16.51
    },
    {
      "epoch": 141,
      "loss": 0.30679843685728436,
      "accuracy": 17.29
    },
    {
      "epoch": 142,
      "loss": 0.3070103922898465,
      "accuracy": 17.74
    },
    {
      "epoch": 143,
      "loss": 0.3048869293420873,
      "accuracy": 17.64
    },
    {
      "epoch": 144,
      "loss": 0.30565047200689927,
      "accuracy": 17.46
    },
    {
      "epoch": 145,
      "loss": 0.3098552978419243,
      "accuracy": 16.97
    },
    {
      "epoch": 146,
      "loss": 0.30688342318889944,
      "accuracy": 17.24
    },
    {
      "epoch": 147,
      "loss": 0.3079857194994358,
      "accuracy": 17.12
    },
    {
      "epoch": 148,
      "loss": 0.30573628893558014,
      "accuracy": 16.55
    },
    {
      "epoch": 149,
      "loss": 0.3073997166245542,
      "accuracy": 16.79
    },
    {
      "epoch": 150,
      "loss": 0.3106934399046796,
      "accuracy": 16.57
    },
    {
      "epoch": 151,
      "loss": 0.3110022948777422,
      "accuracy": 16.51
    },
    {
      "epoch": 152,
      "loss": 0.30736547594374797,
      "accuracy": 17.51
    },
    {
      "epoch": 153,
      "loss": 0.30781519590540135,
      "accuracy": 17.3
    },
    {
      "epoch": 154,
      "loss": 0.30869983720018507,
      "accuracy": 17.35
    },
    {
      "epoch": 155,
      "loss": 0.3069475506531431,
      "accuracy": 18.0
    },
    {
      "epoch": 156,
      "loss": 0.30439789586878835,
      "accuracy": 16.97
    },
    {
      "epoch": 157,
      "loss": 0.30550662678606966,
      "accuracy": 17.2
    },
    {
      "epoch": 158,
      "loss": 0.3051738393116505,
      "accuracy": 17.82
    },
    {
      "epoch": 159,
      "loss": 0.30405692902017145,
      "accuracy": 16.04
    },
    {
      "epoch": 160,
      "loss": 0.3080196402174361,
      "accuracy": 18.26
    },
    {
      "epoch": 161,
      "loss": 0.3035671236033135,
      "accuracy": 17.08
    },
    {
      "epoch": 162,
      "loss": 0.30903783821045083,
      "accuracy": 17.69
    },
    {
      "epoch": 163,
      "loss": 0.3059541844307108,
      "accuracy": 17.66
    },
    {
      "epoch": 164,
      "loss": 0.30664262289696553,
      "accuracy": 17.28
    },
    {
      "epoch": 165,
      "loss": 0.3052082641961727,
      "accuracy": 17.79
    },
    {
      "epoch": 166,
      "loss": 0.3077044558017812,
      "accuracy": 17.74
    },
    {
      "epoch": 167,
      "loss": 0.3055913191526494,
      "accuracy": 18.11
    },
    {
      "epoch": 168,
      "loss": 0.30461093688264806,
      "accuracy": 17.3
    },
    {
      "epoch": 169,
      "loss": 0.3057105942609462,
      "accuracy": 18.09
    },
    {
      "epoch": 170,
      "loss": 0.30444553079123193,
      "accuracy": 18.0
    },
    {
      "epoch": 171,
      "loss": 0.30632696639984214,
      "accuracy": 17.48
    },
    {
      "epoch": 172,
      "loss": 0.30260634834462025,
      "accuracy": 17.72
    },
    {
      "epoch": 173,
      "loss": 0.30302742041171865,
      "accuracy": 17.51
    },
    {
      "epoch": 174,
      "loss": 0.3037938099909336,
      "accuracy": 18.29
    },
    {
      "epoch": 175,
      "loss": 0.30446062848923056,
      "accuracy": 18.0
    },
    {
      "epoch": 176,
      "loss": 0.301382836445849,
      "accuracy": 17.47
    },
    {
      "epoch": 177,
      "loss": 0.3040293931326968,
      "accuracy": 17.63
    },
    {
      "epoch": 178,
      "loss": 0.30346969584835337,
      "accuracy": 17.63
    },
    {
      "epoch": 179,
      "loss": 0.30371999797668864,
      "accuracy": 17.29
    },
    {
      "epoch": 180,
      "loss": 0.3062079038391722,
      "accuracy": 17.92
    },
    {
      "epoch": 181,
      "loss": 0.30414026106925723,
      "accuracy": 17.41
    },
    {
      "epoch": 182,
      "loss": 0.3019812102964584,
      "accuracy": 17.76
    },
    {
      "epoch": 183,
      "loss": 0.30169988020937494,
      "accuracy": 16.74
    },
    {
      "epoch": 184,
      "loss": 0.30314837389803945,
      "accuracy": 16.8
    },
    {
      "epoch": 185,
      "loss": 0.30155996914873734,
      "accuracy": 16.47
    },
    {
      "epoch": 186,
      "loss": 0.30268505773645765,
      "accuracy": 17.76
    },
    {
      "epoch": 187,
      "loss": 0.30143921251626726,
      "accuracy": 18.17
    },
    {
      "epoch": 188,
      "loss": 0.2999329255933457,
      "accuracy": 16.84
    },
    {
      "epoch": 189,
      "loss": 0.30440074420989827,
      "accuracy": 17.95
    },
    {
      "epoch": 190,
      "loss": 0.3044035448355878,
      "accuracy": 18.57
    },
    {
      "epoch": 191,
      "loss": 0.3024155813645809,
      "accuracy": 18.14
    },
    {
      "epoch": 192,
      "loss": 0.3017024964094162,
      "accuracy": 17.87
    },
    {
      "epoch": 193,
      "loss": 0.30052768486611386,
      "accuracy": 17.89
    },
    {
      "epoch": 194,
      "loss": 0.30045665565957413,
      "accuracy": 17.06
    },
    {
      "epoch": 195,
      "loss": 0.3029132200048325,
      "accuracy": 17.79
    },
    {
      "epoch": 196,
      "loss": 0.2980154145905312,
      "accuracy": 17.0
    },
    {
      "epoch": 197,
      "loss": 0.3000338480827656,
      "accuracy": 17.74
    },
    {
      "epoch": 198,
      "loss": 0.30009776490165835,
      "accuracy": 17.83
    },
    {
      "epoch": 199,
      "loss": 0.3019503538912915,
      "accuracy": 17.42
    },
    {
      "epoch": 200,
      "loss": 0.30257551654222165,
      "accuracy": 17.46
    },
    {
      "epoch": 201,
      "loss": 0.3042450063406153,
      "accuracy": 18.06
    },
    {
      "epoch": 202,
      "loss": 0.3002085847423432,
      "accuracy": 17.36
    },
    {
      "epoch": 203,
      "loss": 0.2983838513810584,
      "accuracy": 17.96
    },
    {
      "epoch": 204,
      "loss": 0.3016972265344985,
      "accuracy": 17.25
    },
    {
      "epoch": 205,
      "loss": 0.30256718330560844,
      "accuracy": 17.78
    },
    {
      "epoch": 206,
      "loss": 0.3001807507048262,
      "accuracy": 17.81
    },
    {
      "epoch": 207,
      "loss": 0.29985301171211487,
      "accuracy": 18.46
    },
    {
      "epoch": 208,
      "loss": 0.3022485278388287,
      "accuracy": 17.08
    },
    {
      "epoch": 209,
      "loss": 0.30172730487711885,
      "accuracy": 18.01
    },
    {
      "epoch": 210,
      "loss": 0.2995229154825211,
      "accuracy": 16.46
    },
    {
      "epoch": 211,
      "loss": 0.30087859094777003,
      "accuracy": 17.99
    },
    {
      "epoch": 212,
      "loss": 0.30095860973951666,
      "accuracy": 17.71
    },
    {
      "epoch": 213,
      "loss": 0.29964070491334227,
      "accuracy": 17.77
    },
    {
      "epoch": 214,
      "loss": 0.29943293624735895,
      "accuracy": 16.93
    },
    {
      "epoch": 215,
      "loss": 0.29753072908584105,
      "accuracy": 17.88
    },
    {
      "epoch": 216,
      "loss": 0.2962688238696849,
      "accuracy": 17.8
    },
    {
      "epoch": 217,
      "loss": 0.2965105713681972,
      "accuracy": 17.62
    },
    {
      "epoch": 218,
      "loss": 0.30001845366143165,
      "accuracy": 17.67
    },
    {
      "epoch": 219,
      "loss": 0.3026098755445886,
      "accuracy": 17.64
    },
    {
      "epoch": 220,
      "loss": 0.29893415582940935,
      "accuracy": 17.82
    },
    {
      "epoch": 221,
      "loss": 0.2982808378782678,
      "accuracy": 17.9
    },
    {
      "epoch": 222,
      "loss": 0.2986469956154519,
      "accuracy": 17.81
    },
    {
      "epoch": 223,
      "loss": 0.2995823452764369,
      "accuracy": 17.39
    },
    {
      "epoch": 224,
      "loss": 0.3004643127005151,
      "accuracy": 17.92
    },
    {
      "epoch": 225,
      "loss": 0.29810004900110526,
      "accuracy": 18.11
    },
    {
      "epoch": 226,
      "loss": 0.30054792127710706,
      "accuracy": 17.49
    },
    {
      "epoch": 227,
      "loss": 0.30098689807222245,
      "accuracy": 17.71
    },
    {
      "epoch": 228,
      "loss": 0.29847873366893607,
      "accuracy": 17.87
    },
    {
      "epoch": 229,
      "loss": 0.29860181237788913,
      "accuracy": 17.97
    },
    {
      "epoch": 230,
      "loss": 0.30142832125755065,
      "accuracy": 17.76
    },
    {
      "epoch": 231,
      "loss": 0.3000646276676908,
      "accuracy": 18.39
    },
    {
      "epoch": 232,
      "loss": 0.299217877426046,
      "accuracy": 17.91
    },
    {
      "epoch": 233,
      "loss": 0.3001703297838252,
      "accuracy": 17.53
    },
    {
      "epoch": 234,
      "loss": 0.29694208429848895,
      "accuracy": 18.0
    },
    {
      "epoch": 235,
      "loss": 0.2968273824199717,
      "accuracy": 17.57
    },
    {
      "epoch": 236,
      "loss": 0.29914132708564717,
      "accuracy": 16.86
    },
    {
      "epoch": 237,
      "loss": 0.2969689711611322,
      "accuracy": 17.41
    },
    {
      "epoch": 238,
      "loss": 0.29922957899088554,
      "accuracy": 17.89
    },
    {
      "epoch": 239,
      "loss": 0.2976412539786481,
      "accuracy": 17.56
    },
    {
      "epoch": 240,
      "loss": 0.29703051999528357,
      "accuracy": 17.38
    },
    {
      "epoch": 241,
      "loss": 0.29855598490288915,
      "accuracy": 17.94
    },
    {
      "epoch": 242,
      "loss": 0.2968792248596536,
      "accuracy": 17.93
    },
    {
      "epoch": 243,
      "loss": 0.30038148589590763,
      "accuracy": 17.39
    },
    {
      "epoch": 244,
      "loss": 0.2989817420535899,
      "accuracy": 17.82
    },
    {
      "epoch": 245,
      "loss": 0.29694159449415003,
      "accuracy": 17.73
    },
    {
      "epoch": 246,
      "loss": 0.2967714996731028,
      "accuracy": 17.4
    },
    {
      "epoch": 247,
      "loss": 0.29332343358942803,
      "accuracy": 18.0
    },
    {
      "epoch": 248,
      "loss": 0.29684523984472805,
      "accuracy": 17.63
    },
    {
      "epoch": 249,
      "loss": 0.29462367194764155,
      "accuracy": 18.35
    },
    {
      "epoch": 250,
      "loss": 0.2961767932836046,
      "accuracy": 18.16
    },
    {
      "epoch": 251,
      "loss": 0.2966711448545152,
      "accuracy": 17.46
    },
    {
      "epoch": 252,
      "loss": 0.2962828127310631,
      "accuracy": 18.1
    },
    {
      "epoch": 253,
      "loss": 0.2983943482028677,
      "accuracy": 17.82
    },
    {
      "epoch": 254,
      "loss": 0.29807174681349,
      "accuracy": 17.6
    },
    {
      "epoch": 255,
      "loss": 0.2963656253954198,
      "accuracy": 17.39
    },
    {
      "epoch": 256,
      "loss": 0.29600845905060463,
      "accuracy": 18.12
    },
    {
      "epoch": 257,
      "loss": 0.2950793705088027,
      "accuracy": 18.0
    },
    {
      "epoch": 258,
      "loss": 0.2953648864271793,
      "accuracy": 17.9
    },
    {
      "epoch": 259,
      "loss": 0.29661797329466394,
      "accuracy": 17.98
    },
    {
      "epoch": 260,
      "loss": 0.2957751936417945,
      "accuracy": 17.58
    },
    {
      "epoch": 261,
      "loss": 0.29392388786407225,
      "accuracy": 18.04
    },
    {
      "epoch": 262,
      "loss": 0.2965411459511899,
      "accuracy": 17.77
    },
    {
      "epoch": 263,
      "loss": 0.2954173169871594,
      "accuracy": 17.89
    },
    {
      "epoch": 264,
      "loss": 0.2954977672150795,
      "accuracy": 18.34
    },
    {
      "epoch": 265,
      "loss": 0.2980927103377403,
      "accuracy": 17.65
    },
    {
      "epoch": 266,
      "loss": 0.2969535211299328,
      "accuracy": 17.88
    },
    {
      "epoch": 267,
      "loss": 0.2964631743253546,
      "accuracy": 18.42
    },
    {
      "epoch": 268,
      "loss": 0.293926720986975,
      "accuracy": 17.83
    },
    {
      "epoch": 269,
      "loss": 0.2954342117969026,
      "accuracy": 17.74
    },
    {
      "epoch": 270,
      "loss": 0.29603530403147355,
      "accuracy": 16.91
    },
    {
      "epoch": 271,
      "loss": 0.2963769624207882,
      "accuracy": 17.21
    },
    {
      "epoch": 272,
      "loss": 0.2961418546260671,
      "accuracy": 17.82
    },
    {
      "epoch": 273,
      "loss": 0.2955318315232054,
      "accuracy": 17.87
    },
    {
      "epoch": 274,
      "loss": 0.29294003248214723,
      "accuracy": 18.27
    },
    {
      "epoch": 275,
      "loss": 0.2960013428267012,
      "accuracy": 18.25
    },
    {
      "epoch": 276,
      "loss": 0.29297709458685933,
      "accuracy": 17.95
    },
    {
      "epoch": 277,
      "loss": 0.2972032871018065,
      "accuracy": 17.99
    },
    {
      "epoch": 278,
      "loss": 0.29589668804026664,
      "accuracy": 17.5
    },
    {
      "epoch": 279,
      "loss": 0.2935201270149109,
      "accuracy": 17.79
    },
    {
      "epoch": 280,
      "loss": 0.29552559098030656,
      "accuracy": 17.73
    },
    {
      "epoch": 281,
      "loss": 0.2960418003353667,
      "accuracy": 18.03
    },
    {
      "epoch": 282,
      "loss": 0.2951644264003064,
      "accuracy": 18.09
    },
    {
      "epoch": 283,
      "loss": 0.2951535314321518,
      "accuracy": 18.3
    },
    {
      "epoch": 284,
      "loss": 0.29532677810242836,
      "accuracy": 17.19
    },
    {
      "epoch": 285,
      "loss": 0.29405050715233416,
      "accuracy": 18.0
    },
    {
      "epoch": 286,
      "loss": 0.29476838397218824,
      "accuracy": 18.11
    },
    {
      "epoch": 287,
      "loss": 0.29402344997258895,
      "accuracy": 18.44
    },
    {
      "epoch": 288,
      "loss": 0.2949556941047628,
      "accuracy": 17.72
    },
    {
      "epoch": 289,
      "loss": 0.2941982167515349,
      "accuracy": 17.57
    },
    {
      "epoch": 290,
      "loss": 0.29447879696145973,
      "accuracy": 18.2
    },
    {
      "epoch": 291,
      "loss": 0.2948730416120367,
      "accuracy": 18.07
    },
    {
      "epoch": 292,
      "loss": 0.29515931787008937,
      "accuracy": 18.04
    },
    {
      "epoch": 293,
      "loss": 0.2927129035300397,
      "accuracy": 17.0
    },
    {
      "epoch": 294,
      "loss": 0.2931394949238351,
      "accuracy": 17.98
    },
    {
      "epoch": 295,
      "loss": 0.2909654569118581,
      "accuracy": 17.92
    },
    {
      "epoch": 296,
      "loss": 0.2929588589896547,
      "accuracy": 17.73
    },
    {
      "epoch": 297,
      "loss": 0.2920150210565709,
      "accuracy": 17.77
    },
    {
      "epoch": 298,
      "loss": 0.29350021919037433,
      "accuracy": 17.52
    },
    {
      "epoch": 299,
      "loss": 0.2911466234541954,
      "accuracy": 17.8
    },
    {
      "epoch": 300,
      "loss": 0.29325121634818135,
      "accuracy": 17.57
    },
    {
      "epoch": 301,
      "loss": 0.2952929069387152,
      "accuracy": 17.87
    },
    {
      "epoch": 302,
      "loss": 0.2926513320588051,
      "accuracy": 17.29
    },
    {
      "epoch": 303,
      "loss": 0.2917183295526403,
      "accuracy": 17.97
    },
    {
      "epoch": 304,
      "loss": 0.292524798499777,
      "accuracy": 18.2
    },
    {
      "epoch": 305,
      "loss": 0.29472858785314765,
      "accuracy": 17.98
    },
    {
      "epoch": 306,
      "loss": 0.29318461602038526,
      "accuracy": 17.96
    },
    {
      "epoch": 307,
      "loss": 0.2928442489593587,
      "accuracy": 17.07
    },
    {
      "epoch": 308,
      "loss": 0.2914059822229629,
      "accuracy": 17.84
    },
    {
      "epoch": 309,
      "loss": 0.29550440913819254,
      "accuracy": 17.74
    },
    {
      "epoch": 310,
      "loss": 0.2953627723962703,
      "accuracy": 17.87
    },
    {
      "epoch": 311,
      "loss": 0.29105125773460305,
      "accuracy": 17.88
    },
    {
      "epoch": 312,
      "loss": 0.29341056822462286,
      "accuracy": 17.7
    },
    {
      "epoch": 313,
      "loss": 0.29147775553642435,
      "accuracy": 17.83
    },
    {
      "epoch": 314,
      "loss": 0.29381272697702365,
      "accuracy": 18.01
    },
    {
      "epoch": 315,
      "loss": 0.2926619513871822,
      "accuracy": 18.28
    },
    {
      "epoch": 316,
      "loss": 0.29260973575267385,
      "accuracy": 17.52
    },
    {
      "epoch": 317,
      "loss": 0.29203693955502613,
      "accuracy": 17.58
    },
    {
      "epoch": 318,
      "loss": 0.2895617038645643,
      "accuracy": 17.86
    },
    {
      "epoch": 319,
      "loss": 0.29145161300263506,
      "accuracy": 18.19
    },
    {
      "epoch": 320,
      "loss": 0.29202179471228984,
      "accuracy": 17.92
    },
    {
      "epoch": 321,
      "loss": 0.29033839284105506,
      "accuracy": 17.79
    },
    {
      "epoch": 322,
      "loss": 0.2915833848905056,
      "accuracy": 18.77
    },
    {
      "epoch": 323,
      "loss": 0.2926486093947228,
      "accuracy": 17.69
    },
    {
      "epoch": 324,
      "loss": 0.29095793201568276,
      "accuracy": 17.99
    },
    {
      "epoch": 325,
      "loss": 0.2930798775972204,
      "accuracy": 17.87
    },
    {
      "epoch": 326,
      "loss": 0.2904971676303985,
      "accuracy": 17.77
    },
    {
      "epoch": 327,
      "loss": 0.2871572580109251,
      "accuracy": 17.21
    },
    {
      "epoch": 328,
      "loss": 0.29259245452728677,
      "accuracy": 17.97
    },
    {
      "epoch": 329,
      "loss": 0.2906221842195125,
      "accuracy": 18.03
    },
    {
      "epoch": 330,
      "loss": 0.289966965958159,
      "accuracy": 17.87
    },
    {
      "epoch": 331,
      "loss": 0.29217762845627804,
      "accuracy": 17.97
    },
    {
      "epoch": 332,
      "loss": 0.29020284575984834,
      "accuracy": 18.02
    },
    {
      "epoch": 333,
      "loss": 0.28942385287360944,
      "accuracy": 17.94
    },
    {
      "epoch": 334,
      "loss": 0.29078598827757735,
      "accuracy": 18.55
    },
    {
      "epoch": 335,
      "loss": 0.2911534034191294,
      "accuracy": 17.82
    },
    {
      "epoch": 336,
      "loss": 0.28971927844463513,
      "accuracy": 18.37
    },
    {
      "epoch": 337,
      "loss": 0.28778288056875795,
      "accuracy": 18.01
    },
    {
      "epoch": 338,
      "loss": 0.29006688727977425,
      "accuracy": 18.09
    },
    {
      "epoch": 339,
      "loss": 0.29132660573467295,
      "accuracy": 18.01
    },
    {
      "epoch": 340,
      "loss": 0.2879144901290853,
      "accuracy": 17.58
    },
    {
      "epoch": 341,
      "loss": 0.2903412420698937,
      "accuracy": 18.2
    },
    {
      "epoch": 342,
      "loss": 0.29079386056103607,
      "accuracy": 18.0
    },
    {
      "epoch": 343,
      "loss": 0.29006936061889566,
      "accuracy": 17.37
    },
    {
      "epoch": 344,
      "loss": 0.29249937705537105,
      "accuracy": 17.96
    },
    {
      "epoch": 345,
      "loss": 0.290601129798179,
      "accuracy": 18.25
    },
    {
      "epoch": 346,
      "loss": 0.28976404685923396,
      "accuracy": 17.7
    },
    {
      "epoch": 347,
      "loss": 0.28944845998540836,
      "accuracy": 17.58
    },
    {
      "epoch": 348,
      "loss": 0.2896458956155371,
      "accuracy": 17.22
    },
    {
      "epoch": 349,
      "loss": 0.2888259785606506,
      "accuracy": 17.66
    },
    {
      "epoch": 350,
      "loss": 0.2903748133081071,
      "accuracy": 17.91
    },
    {
      "epoch": 351,
      "loss": 0.2881752197412734,
      "accuracy": 18.18
    },
    {
      "epoch": 352,
      "loss": 0.28776913253550834,
      "accuracy": 17.69
    },
    {
      "epoch": 353,
      "loss": 0.2883229669421277,
      "accuracy": 17.9
    },
    {
      "epoch": 354,
      "loss": 0.28814333940440034,
      "accuracy": 17.88
    },
    {
      "epoch": 355,
      "loss": 0.28809664667920865,
      "accuracy": 18.31
    },
    {
      "epoch": 356,
      "loss": 0.2868557647187659,
      "accuracy": 17.81
    },
    {
      "epoch": 357,
      "loss": 0.2881978899874586,
      "accuracy": 17.88
    },
    {
      "epoch": 358,
      "loss": 0.28943758010864257,
      "accuracy": 17.51
    },
    {
      "epoch": 359,
      "loss": 0.2888554296594985,
      "accuracy": 18.43
    },
    {
      "epoch": 360,
      "loss": 0.28913026414018994,
      "accuracy": 17.69
    },
    {
      "epoch": 361,
      "loss": 0.28925184636039936,
      "accuracy": 18.22
    },
    {
      "epoch": 362,
      "loss": 0.28584488148384907,
      "accuracy": 18.09
    },
    {
      "epoch": 363,
      "loss": 0.28771249575817837,
      "accuracy": 18.3
    },
    {
      "epoch": 364,
      "loss": 0.29008523974012823,
      "accuracy": 17.93
    },
    {
      "epoch": 365,
      "loss": 0.28615674287714854,
      "accuracy": 18.05
    },
    {
      "epoch": 366,
      "loss": 0.2868277557352756,
      "accuracy": 17.87
    },
    {
      "epoch": 367,
      "loss": 0.286449641116122,
      "accuracy": 18.09
    },
    {
      "epoch": 368,
      "loss": 0.28537899579139464,
      "accuracy": 18.11
    },
    {
      "epoch": 369,
      "loss": 0.2879268345680643,
      "accuracy": 17.73
    },
    {
      "epoch": 370,
      "loss": 0.2876857101283175,
      "accuracy": 17.62
    },
    {
      "epoch": 371,
      "loss": 0.28997116944891344,
      "accuracy": 17.6
    },
    {
      "epoch": 372,
      "loss": 0.28837204068265065,
      "accuracy": 17.68
    },
    {
      "epoch": 373,
      "loss": 0.28958643846055293,
      "accuracy": 17.65
    },
    {
      "epoch": 374,
      "loss": 0.2870559206351321,
      "accuracy": 17.93
    },
    {
      "epoch": 375,
      "loss": 0.2868306083248017,
      "accuracy": 17.93
    },
    {
      "epoch": 376,
      "loss": 0.2877644348651805,
      "accuracy": 17.86
    },
    {
      "epoch": 377,
      "loss": 0.2887058912439549,
      "accuracy": 18.1
    },
    {
      "epoch": 378,
      "loss": 0.28737377327807406,
      "accuracy": 17.78
    },
    {
      "epoch": 379,
      "loss": 0.28612944800803003,
      "accuracy": 17.95
    },
    {
      "epoch": 380,
      "loss": 0.28920932342397404,
      "accuracy": 17.81
    },
    {
      "epoch": 381,
      "loss": 0.2873987283478392,
      "accuracy": 17.47
    },
    {
      "epoch": 382,
      "loss": 0.28782110226915236,
      "accuracy": 17.85
    },
    {
      "epoch": 383,
      "loss": 0.2844970769704656,
      "accuracy": 17.73
    },
    {
      "epoch": 384,
      "loss": 0.2865470276233998,
      "accuracy": 17.98
    },
    {
      "epoch": 385,
      "loss": 0.28481431020067094,
      "accuracy": 17.57
    },
    {
      "epoch": 386,
      "loss": 0.2872076410562434,
      "accuracy": 17.74
    },
    {
      "epoch": 387,
      "loss": 0.28537747809227476,
      "accuracy": 17.6
    },
    {
      "epoch": 388,
      "loss": 0.2871708537669892,
      "accuracy": 17.54
    },
    {
      "epoch": 389,
      "loss": 0.28820587453689983,
      "accuracy": 17.8
    },
    {
      "epoch": 390,
      "loss": 0.2874279429937931,
      "accuracy": 17.72
    },
    {
      "epoch": 391,
      "loss": 0.2858728296579199,
      "accuracy": 17.55
    },
    {
      "epoch": 392,
      "loss": 0.2868256202720581,
      "accuracy": 17.83
    },
    {
      "epoch": 393,
      "loss": 0.28632441454745355,
      "accuracy": 17.55
    },
    {
      "epoch": 394,
      "loss": 0.2863282532451001,
      "accuracy": 17.68
    },
    {
      "epoch": 395,
      "loss": 0.28588895366546957,
      "accuracy": 17.57
    },
    {
      "epoch": 396,
      "loss": 0.2869179423819197,
      "accuracy": 17.92
    },
    {
      "epoch": 397,
      "loss": 0.283399739417624,
      "accuracy": 17.81
    },
    {
      "epoch": 398,
      "loss": 0.2856603480082877,
      "accuracy": 17.86
    },
    {
      "epoch": 399,
      "loss": 0.2847271683368277,
      "accuracy": 17.92
    },
    {
      "epoch": 400,
      "loss": 0.2880781357592725,
      "accuracy": 17.89
    },
    {
      "epoch": 401,
      "loss": 0.28707924875173163,
      "accuracy": 17.89
    },
    {
      "epoch": 402,
      "loss": 0.28582476174577753,
      "accuracy": 18.25
    },
    {
      "epoch": 403,
      "loss": 0.2846275323248924,
      "accuracy": 18.18
    },
    {
      "epoch": 404,
      "loss": 0.2863911698473261,
      "accuracy": 17.74
    },
    {
      "epoch": 405,
      "loss": 0.2849149170708149,
      "accuracy": 18.07
    },
    {
      "epoch": 406,
      "loss": 0.28320799479459197,
      "accuracy": 17.77
    },
    {
      "epoch": 407,
      "loss": 0.285315100753561,
      "accuracy": 17.98
    },
    {
      "epoch": 408,
      "loss": 0.2832316226147591,
      "accuracy": 17.9
    },
    {
      "epoch": 409,
      "loss": 0.28294920337961077,
      "accuracy": 18.36
    },
    {
      "epoch": 410,
      "loss": 0.28640701136690505,
      "accuracy": 17.96
    },
    {
      "epoch": 411,
      "loss": 0.28564794431341456,
      "accuracy": 17.99
    },
    {
      "epoch": 412,
      "loss": 0.2847152117719042,
      "accuracy": 18.11
    },
    {
      "epoch": 413,
      "loss": 0.2842091054358381,
      "accuracy": 18.21
    },
    {
      "epoch": 414,
      "loss": 0.28413381370458196,
      "accuracy": 17.8
    },
    {
      "epoch": 415,
      "loss": 0.28501661476936746,
      "accuracy": 17.7
    },
    {
      "epoch": 416,
      "loss": 0.2870381196762653,
      "accuracy": 18.21
    },
    {
      "epoch": 417,
      "loss": 0.2838202246960173,
      "accuracy": 17.63
    },
    {
      "epoch": 418,
      "loss": 0.2834096093127068,
      "accuracy": 17.85
    },
    {
      "epoch": 419,
      "loss": 0.2827932500141732,
      "accuracy": 17.77
    },
    {
      "epoch": 420,
      "loss": 0.2842252227854221,
      "accuracy": 17.82
    },
    {
      "epoch": 421,
      "loss": 0.2859243301952139,
      "accuracy": 17.75
    },
    {
      "epoch": 422,
      "loss": 0.2826806245966161,
      "accuracy": 17.83
    },
    {
      "epoch": 423,
      "loss": 0.28431144832296573,
      "accuracy": 17.88
    },
    {
      "epoch": 424,
      "loss": 0.2841690494025007,
      "accuracy": 17.54
    },
    {
      "epoch": 425,
      "loss": 0.2859902894877373,
      "accuracy": 17.68
    },
    {
      "epoch": 426,
      "loss": 0.2827986383374701,
      "accuracy": 17.55
    },
    {
      "epoch": 427,
      "loss": 0.28405396893937535,
      "accuracy": 17.59
    },
    {
      "epoch": 428,
      "loss": 0.28341152953340654,
      "accuracy": 18.22
    },
    {
      "epoch": 429,
      "loss": 0.2825164260065302,
      "accuracy": 17.85
    },
    {
      "epoch": 430,
      "loss": 0.28401584942290126,
      "accuracy": 17.96
    },
    {
      "epoch": 431,
      "loss": 0.2840837519219581,
      "accuracy": 17.86
    },
    {
      "epoch": 432,
      "loss": 0.28345092236995695,
      "accuracy": 17.84
    },
    {
      "epoch": 433,
      "loss": 0.2845264729350171,
      "accuracy": 17.64
    },
    {
      "epoch": 434,
      "loss": 0.2845789190302504,
      "accuracy": 17.82
    },
    {
      "epoch": 435,
      "loss": 0.2844492993456252,
      "accuracy": 17.44
    },
    {
      "epoch": 436,
      "loss": 0.2817429803787394,
      "accuracy": 17.77
    },
    {
      "epoch": 437,
      "loss": 0.28176996609632005,
      "accuracy": 18.02
    },
    {
      "epoch": 438,
      "loss": 0.28261242109410306,
      "accuracy": 17.84
    },
    {
      "epoch": 439,
      "loss": 0.2826543541347727,
      "accuracy": 17.92
    },
    {
      "epoch": 440,
      "loss": 0.28382287837089376,
      "accuracy": 18.0
    },
    {
      "epoch": 441,
      "loss": 0.284017044496029,
      "accuracy": 17.82
    },
    {
      "epoch": 442,
      "loss": 0.28240762872898834,
      "accuracy": 18.19
    },
    {
      "epoch": 443,
      "loss": 0.2834192817198469,
      "accuracy": 17.89
    },
    {
      "epoch": 444,
      "loss": 0.2819244786145839,
      "accuracy": 17.97
    },
    {
      "epoch": 445,
      "loss": 0.283341091205465,
      "accuracy": 17.75
    },
    {
      "epoch": 446,
      "loss": 0.28353710054083076,
      "accuracy": 17.97
    },
    {
      "epoch": 447,
      "loss": 0.2838880196530768,
      "accuracy": 17.69
    },
    {
      "epoch": 448,
      "loss": 0.2828532939261578,
      "accuracy": 17.76
    },
    {
      "epoch": 449,
      "loss": 0.28137608392441527,
      "accuracy": 17.94
    },
    {
      "epoch": 450,
      "loss": 0.2829406240519057,
      "accuracy": 17.67
    },
    {
      "epoch": 451,
      "loss": 0.2803360804598382,
      "accuracy": 17.87
    },
    {
      "epoch": 452,
      "loss": 0.28388284568456895,
      "accuracy": 17.85
    },
    {
      "epoch": 453,
      "loss": 0.2833421890722944,
      "accuracy": 17.74
    },
    {
      "epoch": 454,
      "loss": 0.2818848516078705,
      "accuracy": 17.71
    },
    {
      "epoch": 455,
      "loss": 0.2820833106624319,
      "accuracy": 17.69
    },
    {
      "epoch": 456,
      "loss": 0.28191370152412576,
      "accuracy": 17.8
    },
    {
      "epoch": 457,
      "loss": 0.28155143368751445,
      "accuracy": 17.73
    },
    {
      "epoch": 458,
      "loss": 0.2836725667119026,
      "accuracy": 17.76
    },
    {
      "epoch": 459,
      "loss": 0.2825768440961838,
      "accuracy": 17.72
    },
    {
      "epoch": 460,
      "loss": 0.27999641394361535,
      "accuracy": 17.81
    },
    {
      "epoch": 461,
      "loss": 0.28128560559546695,
      "accuracy": 17.87
    },
    {
      "epoch": 462,
      "loss": 0.2815870677537106,
      "accuracy": 17.83
    },
    {
      "epoch": 463,
      "loss": 0.2803873766292917,
      "accuracy": 17.9
    },
    {
      "epoch": 464,
      "loss": 0.2814006891656429,
      "accuracy": 17.83
    },
    {
      "epoch": 465,
      "loss": 0.2828764692900029,
      "accuracy": 17.8
    },
    {
      "epoch": 466,
      "loss": 0.28061203211545943,
      "accuracy": 17.86
    },
    {
      "epoch": 467,
      "loss": 0.2807319593556384,
      "accuracy": 17.91
    },
    {
      "epoch": 468,
      "loss": 0.282612629139677,
      "accuracy": 17.87
    },
    {
      "epoch": 469,
      "loss": 0.2805099046610771,
      "accuracy": 17.78
    },
    {
      "epoch": 470,
      "loss": 0.28100419279108657,
      "accuracy": 17.9
    },
    {
      "epoch": 471,
      "loss": 0.2803555408056746,
      "accuracy": 17.82
    },
    {
      "epoch": 472,
      "loss": 0.28128509337597707,
      "accuracy": 17.87
    },
    {
      "epoch": 473,
      "loss": 0.2828417758675332,
      "accuracy": 17.88
    },
    {
      "epoch": 474,
      "loss": 0.28020658962270045,
      "accuracy": 17.85
    },
    {
      "epoch": 475,
      "loss": 0.2824355412987953,
      "accuracy": 17.83
    },
    {
      "epoch": 476,
      "loss": 0.2834165245294571,
      "accuracy": 17.86
    },
    {
      "epoch": 477,
      "loss": 0.28028047011887774,
      "accuracy": 17.86
    },
    {
      "epoch": 478,
      "loss": 0.281163586105438,
      "accuracy": 17.76
    },
    {
      "epoch": 479,
      "loss": 0.2825724112543654,
      "accuracy": 17.79
    },
    {
      "epoch": 480,
      "loss": 0.2808945076262697,
      "accuracy": 17.78
    },
    {
      "epoch": 481,
      "loss": 0.2810715355771653,
      "accuracy": 17.9
    },
    {
      "epoch": 482,
      "loss": 0.28038367679778564,
      "accuracy": 17.82
    },
    {
      "epoch": 483,
      "loss": 0.2801983811119769,
      "accuracy": 17.87
    },
    {
      "epoch": 484,
      "loss": 0.28106516640871126,
      "accuracy": 17.86
    },
    {
      "epoch": 485,
      "loss": 0.2803522995177736,
      "accuracy": 17.86
    },
    {
      "epoch": 486,
      "loss": 0.27971860471558063,
      "accuracy": 17.84
    },
    {
      "epoch": 487,
      "loss": 0.28141945822441833,
      "accuracy": 17.82
    },
    {
      "epoch": 488,
      "loss": 0.2810831311535328,
      "accuracy": 17.86
    },
    {
      "epoch": 489,
      "loss": 0.27959264336114237,
      "accuracy": 17.86
    },
    {
      "epoch": 490,
      "loss": 0.2832174701259491,
      "accuracy": 17.88
    },
    {
      "epoch": 491,
      "loss": 0.2829040657966695,
      "accuracy": 17.87
    },
    {
      "epoch": 492,
      "loss": 0.2807383619090344,
      "accuracy": 17.87
    },
    {
      "epoch": 493,
      "loss": 0.28155154443167624,
      "accuracy": 17.87
    },
    {
      "epoch": 494,
      "loss": 0.28075540896425855,
      "accuracy": 17.87
    },
    {
      "epoch": 495,
      "loss": 0.2801202957617476,
      "accuracy": 17.87
    },
    {
      "epoch": 496,
      "loss": 0.28052552374119455,
      "accuracy": 17.87
    },
    {
      "epoch": 497,
      "loss": 0.2814200473592636,
      "accuracy": 17.87
    },
    {
      "epoch": 498,
      "loss": 0.28204538714378435,
      "accuracy": 17.87
    },
    {
      "epoch": 499,
      "loss": 0.2814529222376803,
      "accuracy": 17.87
    }
  ]
}